bitcoinrpc/.gitignore
bitcoinrpc/__init__.py
bitcoinrpc/authproxy.py
python_bitcoinrpc_2sat-1.0.1.dist-info/licenses/LICENSE
python_bitcoinrpc_2sat-1.0.1.dist-info/METADATA
python_bitcoinrpc_2sat-1.0.1.dist-info/WHEEL
python_bitcoinrpc_2sat-1.0.1.dist-info/top_level.txt
python_bitcoinrpc_2sat-1.0.1.dist-info/RECORD
