Metadata-Version: 2.4
Name: python-bitcoinrpc-2sat
Version: 1.0.1
Summary: Enhanced version of python-jsonrpc for use with Bitcoin
Author-email: Jeff Garzik <jgarzik@pobox.com>
Maintainer-email: twosatsmaxi <jgarzik@pobox.com>
License: LGPL
Project-URL: Homepage, https://github.com/twosatsmaxi/python-bitcoinrpc-2sat
Project-URL: Repository, https://github.com/twosatsmaxi/python-bitcoinrpc-2sat
Project-URL: Issues, https://github.com/twosatsmaxi/python-bitcoinrpc-2sat/issues
Classifier: License :: OSI Approved :: GNU Library or Lesser General Public License (LGPL)
Classifier: Operating System :: OS Independent
Classifier: Programming Language :: Python :: 3
Classifier: Programming Language :: Python :: 3.7
Classifier: Programming Language :: Python :: 3.8
Classifier: Programming Language :: Python :: 3.9
Classifier: Programming Language :: Python :: 3.10
Classifier: Programming Language :: Python :: 3.11
Classifier: Programming Language :: Python :: 3.12
Classifier: Development Status :: 5 - Production/Stable
Classifier: Intended Audience :: Developers
Classifier: Topic :: Software Development :: Libraries :: Python Modules
Requires-Python: >=3.7
License-File: LICENSE
Dynamic: license-file
